{
  "notes": [
    {
      "id": "1",
      "content": "custom-hooks are awesome!"
    },
    {
      "id": "2",
      "content": "best feature ever <3"
    },
    {
      "id": "02e5",
      "content": "i love this feature"
    },
    {
      "id": "0f93",
      "content": "epic"
    }
  ],
  "persons": [
    {
      "id": "1",
      "name": "mluukkai",
      "number": "040-5483923"
    },
    {
      "id": "2",
      "name": "hellas",
      "number": "012-123123"
    },
    {
      "id": "5908",
      "name": "sdasd",
      "number": "dsds"
    },
    {
      "id": "6449",
      "name": "sdasd",
      "number": "dsds"
    },
    {
      "id": "85ff",
      "name": "sdasd",
      "number": "232332"
    },
    {
      "id": "3686",
      "name": "sdasd",
      "number": "232332"
    },
    {
      "id": "3d4c",
      "name": "sdasd",
      "number": "232332"
    },
    {
      "id": "111a",
      "name": "dsadas",
      "number": "22323232323232"
    },
    {
      "id": "63a7",
      "name": "dsadas",
      "number": "22323232323232"
    },
    {
      "id": "97b2",
      "name": "dsadas",
      "number": "22323232323232"
    },
    {
      "id": "386b",
      "name": "dsadas",
      "number": "22323232323232"
    },
    {
      "id": "030e",
      "name": "dsadas",
      "number": "22323232323232"
    },
    {
      "id": "d03b"
    },
    {
      "id": "1938"
    },
    {
      "id": "dcb0"
    },
    {
      "id": "4741"
    },
    {
      "id": "ecf6",
      "name": "twewe",
      "number": "2323232"
    },
    {
      "id": "2c8b",
      "name": "twewe",
      "number": "2323232"
    },
    {
      "id": "7372",
      "name": "hello",
      "number": "123123"
    },
    {
      "id": "51f4",
      "name": "ewew",
      "number": "232323"
    },
    {
      "id": "edea",
      "name": "hi",
      "number": "123123"
    },
    {
      "id": "4b86",
      "name": "dsdsd",
      "number": "dsdsdsd"
    }
  ]
}